Extra Credit/TrafficLite.v
module TrafficLite(EWCar, NSCar, EWLite, NSLite, clock); //input and output
    input EWCar, NSCar, clock;
    output EWLite; 
    output NSLite;

    reg state;
    initial state = 0; //set initial state

    //following two assignments set the output, which is based only on the state variable
    assign NSLite = ~state; //NSLite on if state = 0
    assign EWLite = state;  //EWLite on if state = 1

    always @(posedge clock) //all state updates on a positive clock edge
        case (state)
            0: state = EWCar; //change state only if EWCar
            1: state = ~NSCar; //change state only if NSCar
        endcase
endmodule

Extra Credit/TrafficLite_tb.v
`timescale 1ns / 1ns
`include "TrafficLite.v"

module TrafficLite_tb;

reg EWCar;
reg NSCar;
reg clock;
wire EWLite;
wire NSLite;

TrafficLite uut(EWCar, NSCar, EWLite, NSLite, clock);


initial begin
    $dumpfile("TrafficLite_tb.vcd");
    $dumpvars(0, TrafficLite_tb);

    // Clock 1
    EWCar = 0;
    NSCar = 0;
    clock = 0;
    #10

    // Clock 2
    EWCar = 0;
    NSCar = 0;
    clock = 1;
    #10

    // Clock 3
    EWCar = 1;
    NSCar = 0;
    clock = 0;
    #10
    
    // Clock 4
    EWCar = 1;
    NSCar = 0;
    clock = 1;
    #10

    // Clock 5
    EWCar = 1;
    NSCar = 1;
    clock = 0;
    #10

    // Clock 6
    EWCar = 1;
    NSCar = 1;
    clock = 1;
    #10

    // Clock 7
    EWCar = 0;
    NSCar = 1;
    clock = 0;
    #10
    
    // Clock 8
    EWCar = 0;
    NSCar = 1;
    clock = 1;
    #10

    // Clock 9
    EWCar = 0;
    NSCar = 0;
    clock = 0;
    #10

    // Clock 10
    EWCar = 0;
    NSCar = 0;
    clock = 1;
    #10

    // Clock 11
    EWCar = 1;
    NSCar = 0;
    clock = 0;
    #10
    
    // Clock 12
    EWCar = 1;
    NSCar = 0;
    clock = 1;
    #10
    
    // Clock 12
    EWCar = 1;
    NSCar = 0;
    clock = 0;
    #10
    
    $display("Test Complete");
end

endmodule

Extra Credit/TrafficLite_tb.vcd
$date
	Fri Oct 14 15:50:02 2022
$end
$version
	Icarus Verilog
$end
$timescale
	1ns
$end
$scope module TrafficLite_tb $end
$var wire 1 ! NSLite $end
$var wire 1 " EWLite $end
$var reg 1 # EWCar $end
$var reg 1 $ NSCar $end
$var reg 1 % clock $end
$scope module uut $end
$var wire 1 # EWCar $end
$var wire 1 " EWLite $end
$var wire 1 $ NSCar $end
$var wire 1 ! NSLite $end
$var wire 1 % clock $end
$var reg 1 & state $end
$upscope $end
$upscope $end
$enddefinitions $end
$comment Show the parameter values. $end
$dumpall
$end
#0
$dumpvars
0&
0%
0$
0#
0"
1!
$end
#10
1%
#20
0%
1#
#30
0!
1"
1&
1%
#40
0%
1$
#50
1!
0"
0&
1%
#60
0%
0#
#70
1%
#80
0%
0$
#90
1%
#100
0%
1#
#110
0!
1"
1&
1%
